szj_t_p/__init__.py
szj_t_p/szj_t_p.py
szj_t_p-0.0.1.dist-info/LICENSE
szj_t_p-0.0.1.dist-info/METADATA
szj_t_p-0.0.1.dist-info/WHEEL
szj_t_p-0.0.1.dist-info/top_level.txt
szj_t_p-0.0.1.dist-info/RECORD
